<?xml version="1.0" encoding="UTF-8"?>
<anychart>
	<margin all="3" bottom="0"  left="10" right="8"/>
	<settings>
		<locale>
			<date_time_format>
				<format>%u</format>
				<week_days start_from="Sunday">
				 <short_names><![CDATA[So.,Mo.,Di.,Mi.,Do.,Fr.,Sa.]]></short_names>
				</week_days>				
			</date_time_format>
		</locale>

	</settings>

	<charts>
		<chart plot_type="Scatter">
			<chart_settings>
				<title enabled="false" />
				<axes>
					<x_axis>
						<scale type="DateTime" minimum_offset="0" maximum_offset="0"
							minor_interval="3" minor_interval_unit="Hour" major_interval="1"
							major_interval_unit="Day" />

						<title enabled="false" />
						<labels enabled="True" show_cross_label="True" allow_overlap="true">
							<format><![CDATA[                ]]>{%Value}{dateTimeFormat:%ddd %dd.%MM.}</format>
							<font family="Arial" color="#444444" size="11" />
						</labels>
						<major_grid enabled="True" interlaced="True">
							<interlaced_fills>
								<even>
									<fill color="rgb(245,245,245)" opacity="1" />
								</even>
							</interlaced_fills>
						</major_grid>
					</x_axis>
					<y_axis>

						<title enabled="false" />
						<labels>
							<format>{%Value}{numDecimals:0} </format>
							<font family="Arial" color="#444444" size="11" />
						</labels>
					</y_axis>

					<extra>
						<y_axis name="y2" enabled="False">

							<title enabled="false" />
							<labels>
								<format></format>
							</labels>
						</y_axis>
					</extra>

				</axes>
				<chart_background enabled="false">
					<effects enabled="false" />

					<border enabled="false" />
					<inside_margin all="0" />
				</chart_background>
				<data_plot_background enabled="false">
					<effects enabled="false" />
				</data_plot_background>
			</chart_settings>

			<data_plot_settings default_series_type="Spline">

				<line_series>

					<marker_settings enabled="false" />

					<line_style>
						<line enabled="true" thickness="2" caps="round" joints="round" />
					</line_style>

				</line_series>

			</data_plot_settings>
			<styles>
				<line_style name="ffline" color="#966400" />
				<line_style name="fgline" color="#c800aa" />
			</styles>
			<data>
				<series name="80b" style="ffline" use_hand_cursor="False" hoverable="False">
					<point name="1334707200" x="1334707200" y="0" /> <!--2012-04-18 00:00.00 +00:00 -->
<point name="1334718000" x="1334718000" y="0" /> <!--2012-04-18 03:00.00 +00:00 -->
<point name="1334728800" x="1334728800" y="0" /> <!--2012-04-18 06:00.00 +00:00 -->
<point name="1334739600" x="1334739600" y="2" /> <!--2012-04-18 09:00.00 +00:00 -->
<point name="1334750400" x="1334750400" y="4" /> <!--2012-04-18 12:00.00 +00:00 -->
<point name="1334761200" x="1334761200" y="4" /> <!--2012-04-18 15:00.00 +00:00 -->
<point name="1334772000" x="1334772000" y="2" /> <!--2012-04-18 18:00.00 +00:00 -->
<point name="1334782800" x="1334782800" y="1" /> <!--2012-04-18 21:00.00 +00:00 -->
<point name="1334793600" x="1334793600" y="1" /> <!--2012-04-19 00:00.00 +00:00 -->
<point name="1334804400" x="1334804400" y="1" /> <!--2012-04-19 03:00.00 +00:00 -->
<point name="1334815200" x="1334815200" y="1" /> <!--2012-04-19 06:00.00 +00:00 -->
<point name="1334826000" x="1334826000" y="2" /> <!--2012-04-19 09:00.00 +00:00 -->
<point name="1334836800" x="1334836800" y="5" /> <!--2012-04-19 12:00.00 +00:00 -->
<point name="1334847600" x="1334847600" y="3" /> <!--2012-04-19 15:00.00 +00:00 -->
<point name="1334858400" x="1334858400" y="2" /> <!--2012-04-19 18:00.00 +00:00 -->
<point name="1334869200" x="1334869200" y="1" /> <!--2012-04-19 21:00.00 +00:00 -->
<point name="1334880000" x="1334880000" y="1" /> <!--2012-04-20 00:00.00 +00:00 -->
<point name="1334890800" x="1334890800" y="1" /> <!--2012-04-20 03:00.00 +00:00 -->
<point name="1334901600" x="1334901600" y="1" /> <!--2012-04-20 06:00.00 +00:00 -->
<point name="1334912400" x="1334912400" y="3" /> <!--2012-04-20 09:00.00 +00:00 -->
<point name="1334923200" x="1334923200" y="10" /> <!--2012-04-20 12:00.00 +00:00 -->
<point name="1334934000" x="1334934000" y="10" /> <!--2012-04-20 15:00.00 +00:00 -->
<point name="1334944800" x="1334944800" y="8" /> <!--2012-04-20 18:00.00 +00:00 -->
<point name="1334955600" x="1334955600" y="3" /> <!--2012-04-20 21:00.00 +00:00 -->
<point name="1334966400" x="1334966400" y="2" /> <!--2012-04-21 00:00.00 +00:00 -->
<point name="1334977200" x="1334977200" y="3" /> <!--2012-04-21 03:00.00 +00:00 -->
<point name="1334988000" x="1334988000" y="2" /> <!--2012-04-21 06:00.00 +00:00 -->
<point name="1334998800" x="1334998800" y="5" /> <!--2012-04-21 09:00.00 +00:00 -->
<point name="1335009600" x="1335009600" y="10" /> <!--2012-04-21 12:00.00 +00:00 -->
<point name="1335020400" x="1335020400" y="9" /> <!--2012-04-21 15:00.00 +00:00 -->
<point name="1335031200" x="1335031200" y="5" /> <!--2012-04-21 18:00.00 +00:00 -->
<point name="1335042000" x="1335042000" y="2" /> <!--2012-04-21 21:00.00 +00:00 -->
<point name="1335052800" x="1335052800" y="2" /> <!--2012-04-22 00:00.00 +00:00 -->
<point name="1335063600" x="1335063600" y="2" /> <!--2012-04-22 03:00.00 +00:00 -->
<point name="1335074400" x="1335074400" y="2" /> <!--2012-04-22 06:00.00 +00:00 -->
<point name="1335085200" x="1335085200" y="4" /> <!--2012-04-22 09:00.00 +00:00 -->
<point name="1335096000" x="1335096000" y="8" /> <!--2012-04-22 12:00.00 +00:00 -->
<point name="1335106800" x="1335106800" y="7" /> <!--2012-04-22 15:00.00 +00:00 -->
<point name="1335117600" x="1335117600" y="5" /> <!--2012-04-22 18:00.00 +00:00 -->
<point name="1335128400" x="1335128400" y="5" /> <!--2012-04-22 21:00.00 +00:00 -->
				</series>
				<series name="80c" style="fgline" use_hand_cursor="False" hoverable="False">
					<point name="1334707200" x="1334707200" y="4" /> <!--2012-04-18 00:00.00 +00:00 -->
<point name="1334718000" x="1334718000" y="4" /> <!--2012-04-18 03:00.00 +00:00 -->
<point name="1334728800" x="1334728800" y="7" /> <!--2012-04-18 06:00.00 +00:00 -->
<point name="1334739600" x="1334739600" y="11" /> <!--2012-04-18 09:00.00 +00:00 -->
<point name="1334750400" x="1334750400" y="19" /> <!--2012-04-18 12:00.00 +00:00 -->
<point name="1334761200" x="1334761200" y="18" /> <!--2012-04-18 15:00.00 +00:00 -->
<point name="1334772000" x="1334772000" y="15" /> <!--2012-04-18 18:00.00 +00:00 -->
<point name="1334782800" x="1334782800" y="9" /> <!--2012-04-18 21:00.00 +00:00 -->
<point name="1334793600" x="1334793600" y="8" /> <!--2012-04-19 00:00.00 +00:00 -->
<point name="1334804400" x="1334804400" y="8" /> <!--2012-04-19 03:00.00 +00:00 -->
<point name="1334815200" x="1334815200" y="9" /> <!--2012-04-19 06:00.00 +00:00 -->
<point name="1334826000" x="1334826000" y="13" /> <!--2012-04-19 09:00.00 +00:00 -->
<point name="1334836800" x="1334836800" y="18" /> <!--2012-04-19 12:00.00 +00:00 -->
<point name="1334847600" x="1334847600" y="22" /> <!--2012-04-19 15:00.00 +00:00 -->
<point name="1334858400" x="1334858400" y="17" /> <!--2012-04-19 18:00.00 +00:00 -->
<point name="1334869200" x="1334869200" y="10" /> <!--2012-04-19 21:00.00 +00:00 -->
<point name="1334880000" x="1334880000" y="8" /> <!--2012-04-20 00:00.00 +00:00 -->
<point name="1334890800" x="1334890800" y="7" /> <!--2012-04-20 03:00.00 +00:00 -->
<point name="1334901600" x="1334901600" y="8" /> <!--2012-04-20 06:00.00 +00:00 -->
<point name="1334912400" x="1334912400" y="12" /> <!--2012-04-20 09:00.00 +00:00 -->
<point name="1334923200" x="1334923200" y="24" /> <!--2012-04-20 12:00.00 +00:00 -->
<point name="1334934000" x="1334934000" y="27" /> <!--2012-04-20 15:00.00 +00:00 -->
<point name="1334944800" x="1334944800" y="23" /> <!--2012-04-20 18:00.00 +00:00 -->
<point name="1334955600" x="1334955600" y="16" /> <!--2012-04-20 21:00.00 +00:00 -->
<point name="1334966400" x="1334966400" y="11" /> <!--2012-04-21 00:00.00 +00:00 -->
<point name="1334977200" x="1334977200" y="10" /> <!--2012-04-21 03:00.00 +00:00 -->
<point name="1334988000" x="1334988000" y="11" /> <!--2012-04-21 06:00.00 +00:00 -->
<point name="1334998800" x="1334998800" y="19" /> <!--2012-04-21 09:00.00 +00:00 -->
<point name="1335009600" x="1335009600" y="30" /> <!--2012-04-21 12:00.00 +00:00 -->
<point name="1335020400" x="1335020400" y="30" /> <!--2012-04-21 15:00.00 +00:00 -->
<point name="1335031200" x="1335031200" y="26" /> <!--2012-04-21 18:00.00 +00:00 -->
<point name="1335042000" x="1335042000" y="20" /> <!--2012-04-21 21:00.00 +00:00 -->
<point name="1335052800" x="1335052800" y="11" /> <!--2012-04-22 00:00.00 +00:00 -->
<point name="1335063600" x="1335063600" y="10" /> <!--2012-04-22 03:00.00 +00:00 -->
<point name="1335074400" x="1335074400" y="14" /> <!--2012-04-22 06:00.00 +00:00 -->
<point name="1335085200" x="1335085200" y="13" /> <!--2012-04-22 09:00.00 +00:00 -->
<point name="1335096000" x="1335096000" y="26" /> <!--2012-04-22 12:00.00 +00:00 -->
<point name="1335106800" x="1335106800" y="27" /> <!--2012-04-22 15:00.00 +00:00 -->
<point name="1335117600" x="1335117600" y="26" /> <!--2012-04-22 18:00.00 +00:00 -->
<point name="1335128400" x="1335128400" y="20" /> <!--2012-04-22 21:00.00 +00:00 -->
				</series>
			</data>
		</chart>
	</charts>
</anychart>